{"id": "c6c422f0c8f292c2e5b5f0ce871a52f7", "sport_key": "soccer_france_ligue_one", "sport_title": "Ligue 1 - France", "commence_time": "2023-06-03T19:00:00Z", "home_team": "Stade de Reims", "away_team": "Montpellier", "bookmakers": [{"key": "onexbet", "title": "1xBet", "markets": [{"key": "totals", "last_update": "2023-06-03T18:29:33Z", "outcomes": [{"name": "Over", "price": 1.99, "point": 3.5}, {"name": "Under", "price": 1.95, "point": 3.5}]}, {"key": "btts", "last_update": "2023-06-03T18:29:33Z", "outcomes": [{"name": "Yes", "price": 1.39}, {"name": "No", "price": 2.89}]}]}, {"key": "pinnacle", "title": "Pinnacle", "markets": [{"key": "totals", "last_update": "2023-06-03T18:29:35Z", "outcomes": [{"name": "Over", "price": 1.97, "point": 3.5}, {"name": "Under", "price": 1.92, "point": 3.5}]}]}, {"key": "matchbook", "title": "Matchbook", "markets": [{"key": "totals", "last_update": "2023-06-03T18:29:44Z", "outcomes": [{"name": "Over", "price": 2.0, "point": 3.5}, {"name": "Under", "price": 1.96, "point": 3.5}]}]}, {"key": "nordicbet", "title": "Nordic Bet", "markets": [{"key": "totals", "last_update": "2023-06-03T18:29:45Z", "outcomes": [{"name": "Over", "price": 1.36, "point": 2.5}, {"name": "Under", "price": 3.2, "point": 2.5}]}]}, {"key": "betonlineag", "title": "BetOnline.ag", "markets": [{"key": "totals", "last_update": "2023-06-03T18:29:25Z", "outcomes": [{"name": "Over", "price": 1.98, "point": 3.5}, {"name": "Under", "price": 1.85, "point": 3.5}]}]}, {"key": "unibet_eu", "title": "Unibet", "markets": [{"key": "totals", "last_update": "2023-06-03T18:29:30Z", "outcomes": [{"name": "Over", "price": 1.87, "point": 3.5}, {"name": "Under", "price": 1.93, "point": 3.5}]}]}]}