{"id": "3bdb24a1157422caa085c3f09c55db42", "sport_key": "soccer_sweden_allsvenskan", "sport_title": "Allsvenskan - Sweden", "commence_time": "2023-09-03T13:00:47Z", "home_team": "Kalmar FF", "away_team": "Mj\u00e4llby AIF", "bookmakers": [{"key": "unibet_eu", "title": "Unibet", "markets": [{"key": "totals", "last_update": "2023-09-03T13:20:08Z", "outcomes": [{"name": "Over", "price": 1.65, "point": 2.5}, {"name": "Under", "price": 2.16, "point": 2.5}]}]}, {"key": "nordicbet", "title": "Nordic Bet", "markets": [{"key": "totals", "last_update": "2023-09-03T13:20:06Z", "outcomes": [{"name": "Over", "price": 20.0, "point": 6.5}, {"name": "Under", "price": 1.0, "point": 6.5}]}]}, {"key": "pinnacle", "title": "Pinnacle", "markets": [{"key": "totals", "last_update": "2023-09-03T13:20:06Z", "outcomes": [{"name": "Over", "price": 2.09, "point": 3.0}, {"name": "Under", "price": 1.81, "point": 3.0}]}]}, {"key": "matchbook", "title": "Matchbook", "markets": [{"key": "totals", "last_update": "2023-09-03T13:20:06Z", "outcomes": [{"name": "Over", "price": 1.71, "point": 2.5}, {"name": "Under", "price": 2.3, "point": 2.5}]}]}]}