{"id": "8295376002fb762edba09bd7ad1c32d9", "sport_key": "soccer_switzerland_superleague", "sport_title": "Swiss Superleague", "commence_time": "2023-09-03T12:16:37Z", "home_team": "Servette", "away_team": "BSC Young Boys", "bookmakers": [{"key": "nordicbet", "title": "Nordic Bet", "markets": [{"key": "totals", "last_update": "2023-09-03T13:29:13Z", "outcomes": [{"name": "Over", "price": 4.9, "point": 3.5}, {"name": "Under", "price": 1.15, "point": 3.5}]}]}, {"key": "pinnacle", "title": "Pinnacle", "markets": [{"key": "totals", "last_update": "2023-09-03T13:29:14Z", "outcomes": [{"name": "Over", "price": 1.85, "point": 2.25}, {"name": "Under", "price": 2.03, "point": 2.25}]}]}, {"key": "unibet_eu", "title": "Unibet", "markets": [{"key": "totals", "last_update": "2023-09-03T13:29:15Z", "outcomes": [{"name": "Over", "price": 2.18, "point": 2.5}, {"name": "Under", "price": 1.63, "point": 2.5}]}]}]}