{"id": "98268a0edb51fe423e1e7229ab73ac4e", "sport_key": "soccer_france_ligue_one", "sport_title": "Ligue 1 - France", "commence_time": "2023-09-03T13:00:04Z", "home_team": "Metz", "away_team": "Stade de Reims", "bookmakers": [{"key": "unibet_eu", "title": "Unibet", "markets": [{"key": "totals", "last_update": "2023-09-03T13:18:59Z", "outcomes": [{"name": "Over", "price": 2.15, "point": 4.5}, {"name": "Under", "price": 1.66, "point": 4.5}]}]}, {"key": "matchbook", "title": "Matchbook", "markets": [{"key": "totals", "last_update": "2023-09-03T13:20:13Z", "outcomes": [{"name": "Over", "price": 2.34, "point": 4.5}, {"name": "Under", "price": 1.7, "point": 4.5}]}]}, {"key": "pinnacle", "title": "Pinnacle", "markets": [{"key": "totals", "last_update": "2023-09-03T13:20:13Z", "outcomes": [{"name": "Over", "price": 1.84, "point": 3.5}, {"name": "Under", "price": 2.04, "point": 3.5}]}]}, {"key": "nordicbet", "title": "Nordic Bet", "markets": [{"key": "totals", "last_update": "2023-09-03T13:20:13Z", "outcomes": [{"name": "Over", "price": 7.6, "point": 6.5}, {"name": "Under", "price": 1.07, "point": 6.5}]}]}]}