{"id": "17d1196aa00a2882171ee86b6ac3d051", "sport_key": "soccer_uefa_champs_league", "sport_title": "UEFA Champions League", "commence_time": "2023-10-03T16:45:15Z", "home_team": "Salzburg", "away_team": "Real Sociedad", "bookmakers": [{"key": "pinnacle", "title": "Pinnacle", "markets": [{"key": "totals", "last_update": "2023-10-03T17:04:43Z", "outcomes": [{"name": "Over", "price": 2.01, "point": 2.75}, {"name": "Under", "price": 1.88, "point": 2.75}]}]}, {"key": "unibet_eu", "title": "Unibet", "markets": [{"key": "totals", "last_update": "2023-10-03T17:04:44Z", "outcomes": [{"name": "Over", "price": 1.68, "point": 2.5}, {"name": "Under", "price": 2.12, "point": 2.5}]}]}, {"key": "matchbook", "title": "Matchbook", "markets": [{"key": "totals", "last_update": "2023-10-03T17:04:43Z", "outcomes": [{"name": "Over", "price": 6.6, "point": 4.5}, {"name": "Under", "price": 1.07, "point": 4.5}]}]}]}