{"id": "a4babf905468b31261cbc2da5209804e", "sport_key": "soccer_usa_mls", "sport_title": "MLS", "commence_time": "2023-10-05T02:30:00Z", "home_team": "Los Angeles FC", "away_team": "Minnesota United FC", "bookmakers": [{"key": "nordicbet", "title": "Nordic Bet", "markets": [{"key": "totals", "last_update": "2023-10-05T02:43:35Z", "outcomes": [{"name": "Over", "price": 1.4, "point": 2.5}, {"name": "Under", "price": 2.8, "point": 2.5}]}]}, {"key": "pinnacle", "title": "Pinnacle", "markets": [{"key": "totals", "last_update": "2023-10-05T02:44:19Z", "outcomes": [{"name": "Over", "price": 1.9, "point": 3.25}, {"name": "Under", "price": 1.98, "point": 3.25}]}]}, {"key": "matchbook", "title": "Matchbook", "markets": [{"key": "totals", "last_update": "2023-10-05T02:45:00Z", "outcomes": [{"name": "Over", "price": 2.14, "point": 3.5}, {"name": "Under", "price": 1.73, "point": 3.5}]}]}, {"key": "betonlineag", "title": "BetOnline.ag", "markets": [{"key": "totals", "last_update": "2023-10-05T02:39:04Z", "outcomes": [{"name": "Over", "price": 1.87, "point": 3.25}, {"name": "Under", "price": 1.95, "point": 3.25}]}]}, {"key": "unibet_eu", "title": "Unibet", "markets": [{"key": "totals", "last_update": "2023-10-05T02:44:45Z", "outcomes": [{"name": "Over", "price": 2.02, "point": 3.5}, {"name": "Under", "price": 1.74, "point": 3.5}]}]}]}