{"id": "f1e1b5d8adbeb723cc543dd5fafcb3c1", "sport_key": "soccer_spain_la_liga", "sport_title": "La Liga - Spain", "commence_time": "2023-05-14T19:00:00Z", "home_team": "Espanyol", "away_team": "Barcelona", "bookmakers": [{"key": "pinnacle", "title": "Pinnacle", "markets": [{"key": "totals", "last_update": "2023-05-14T17:59:30Z", "outcomes": [{"name": "Over", "price": 1.88, "point": 2.75}, {"name": "Under", "price": 2.03, "point": 2.75}]}]}, {"key": "onexbet", "title": "1xBet", "markets": [{"key": "totals", "last_update": "2023-05-14T17:59:45Z", "outcomes": [{"name": "Over", "price": 1.73, "point": 2.5}, {"name": "Under", "price": 2.3, "point": 2.5}]}, {"key": "btts", "last_update": "2023-05-14T17:59:45Z", "outcomes": [{"name": "Yes", "price": 1.75}, {"name": "No", "price": 2.02}]}]}, {"key": "williamhill", "title": "William Hill", "markets": [{"key": "totals", "last_update": "2023-05-14T17:59:44Z", "outcomes": [{"name": "Over", "price": 1.62, "point": 2.5}, {"name": "Under", "price": 2.2, "point": 2.5}]}, {"key": "btts", "last_update": "2023-05-14T17:59:44Z", "outcomes": [{"name": "Yes", "price": 1.73}, {"name": "No", "price": 2.0}]}]}, {"key": "nordicbet", "title": "Nordic Bet", "markets": [{"key": "totals", "last_update": "2023-05-14T17:59:44Z", "outcomes": [{"name": "Over", "price": 1.66, "point": 2.5}, {"name": "Under", "price": 2.25, "point": 2.5}]}]}, {"key": "unibet_eu", "title": "Unibet", "markets": [{"key": "totals", "last_update": "2023-05-14T17:59:46Z", "outcomes": [{"name": "Over", "price": 1.67, "point": 2.5}, {"name": "Under", "price": 2.2, "point": 2.5}]}]}, {"key": "betonlineag", "title": "BetOnline.ag", "markets": [{"key": "totals", "last_update": "2023-05-14T17:59:30Z", "outcomes": [{"name": "Over", "price": 2.15, "point": 3.0}, {"name": "Under", "price": 1.74, "point": 3.0}]}]}, {"key": "matchbook", "title": "Matchbook", "markets": [{"key": "totals", "last_update": "2023-05-14T17:59:45Z", "outcomes": [{"name": "Over", "price": 1.74, "point": 2.5}, {"name": "Under", "price": 2.32, "point": 2.5}]}]}]}