{"id": "ae75b80808b0e4869f61dbfa632f4745", "sport_key": "soccer_portugal_primeira_liga", "sport_title": "Primeira Liga - Portugal", "commence_time": "2023-09-17T14:30:35Z", "home_team": "Gil Vicente", "away_team": "Estoril", "bookmakers": [{"key": "unibet_eu", "title": "Unibet", "markets": [{"key": "totals", "last_update": "2023-09-17T15:44:26Z", "outcomes": [{"name": "Over", "price": 2.25, "point": 6.5}, {"name": "Under", "price": 1.56, "point": 6.5}]}]}, {"key": "nordicbet", "title": "Nordic Bet", "markets": [{"key": "totals", "last_update": "2023-09-17T15:43:02Z", "outcomes": [{"name": "Over", "price": 5.5, "point": 6.5}, {"name": "Under", "price": 1.12, "point": 6.5}]}]}, {"key": "matchbook", "title": "Matchbook", "markets": [{"key": "totals", "last_update": "2023-09-17T15:43:03Z", "outcomes": [{"name": "Over", "price": 2.44, "point": 5.5}, {"name": "Under", "price": 1.57, "point": 5.5}]}]}]}