{"id": "ca1648eeaaa512cf545a3c969ce9ac73", "sport_key": "soccer_austria_bundesliga", "sport_title": "Austrian Football Bundesliga", "commence_time": "2023-09-17T15:01:14Z", "home_team": "Rapid Wien", "away_team": "Wolfsberger AC", "bookmakers": [{"key": "pinnacle", "title": "Pinnacle", "markets": [{"key": "totals", "last_update": "2023-09-17T16:14:49Z", "outcomes": [{"name": "Over", "price": 2.0, "point": 3.5}, {"name": "Under", "price": 1.89, "point": 3.5}]}]}, {"key": "unibet_eu", "title": "Unibet", "markets": [{"key": "totals", "last_update": "2023-09-17T16:14:52Z", "outcomes": [{"name": "Over", "price": 1.93, "point": 3.5}, {"name": "Under", "price": 1.87, "point": 3.5}]}]}]}