{"id": "b042a6f563cf2df55a589e1822d5536a", "sport_key": "soccer_usa_mls", "sport_title": "MLS", "commence_time": "2023-09-20T23:40:00Z", "home_team": "Inter Miami CF", "away_team": "Toronto FC", "bookmakers": [{"key": "williamhill", "title": "William Hill", "markets": [{"key": "totals", "last_update": "2023-09-20T23:29:09Z", "outcomes": [{"name": "Over", "price": 1.36, "point": 2.5}, {"name": "Under", "price": 3.0, "point": 2.5}]}, {"key": "btts", "last_update": "2023-09-20T23:29:09Z", "outcomes": [{"name": "Yes", "price": 1.67}, {"name": "No", "price": 2.1}]}]}, {"key": "nordicbet", "title": "Nordic Bet", "markets": [{"key": "totals", "last_update": "2023-09-20T23:38:24Z", "outcomes": [{"name": "Over", "price": 1.33, "point": 2.5}, {"name": "Under", "price": 3.25, "point": 2.5}]}]}, {"key": "pinnacle", "title": "Pinnacle", "markets": [{"key": "totals", "last_update": "2023-09-20T23:40:12Z", "outcomes": [{"name": "Over", "price": 1.88, "point": 3.5}, {"name": "Under", "price": 1.99, "point": 3.5}]}]}, {"key": "betonlineag", "title": "BetOnline.ag", "markets": [{"key": "totals", "last_update": "2023-09-20T23:40:12Z", "outcomes": [{"name": "Over", "price": 1.86, "point": 3.5}, {"name": "Under", "price": 1.96, "point": 3.5}]}]}, {"key": "matchbook", "title": "Matchbook", "markets": [{"key": "totals", "last_update": "2023-09-20T23:40:12Z", "outcomes": [{"name": "Over", "price": 2.12, "point": 3.5}, {"name": "Under", "price": 1.9, "point": 3.5}]}]}, {"key": "unibet_eu", "title": "Unibet", "markets": [{"key": "totals", "last_update": "2023-09-20T23:39:39Z", "outcomes": [{"name": "Over", "price": 1.88, "point": 3.5}, {"name": "Under", "price": 1.88, "point": 3.5}]}]}]}