{"id": "f5d88450624e02241838ba9da9ee598a", "sport_key": "soccer_italy_serie_a", "sport_title": "Serie A - Italy", "commence_time": "2023-08-20T16:30:00Z", "home_team": "Sassuolo", "away_team": "Atalanta BC", "bookmakers": [{"key": "betonlineag", "title": "BetOnline.ag", "markets": [{"key": "totals", "last_update": "2023-08-20T13:58:02Z", "outcomes": [{"name": "Over", "price": 1.85, "point": 2.75}, {"name": "Under", "price": 1.98, "point": 2.75}]}]}, {"key": "onexbet", "title": "1xBet", "markets": [{"key": "totals", "last_update": "2023-08-20T13:55:07Z", "outcomes": [{"name": "Over", "price": 1.69, "point": 2.5}, {"name": "Under", "price": 2.36, "point": 2.5}]}, {"key": "btts", "last_update": "2023-08-20T13:55:07Z", "outcomes": [{"name": "Yes", "price": 1.55}, {"name": "No", "price": 2.38}]}]}, {"key": "pinnacle", "title": "Pinnacle", "markets": [{"key": "totals", "last_update": "2023-08-20T13:58:02Z", "outcomes": [{"name": "Over", "price": 2.08, "point": 3.0}, {"name": "Under", "price": 1.83, "point": 3.0}]}]}, {"key": "williamhill", "title": "William Hill", "markets": [{"key": "totals", "last_update": "2023-08-20T13:58:58Z", "outcomes": [{"name": "Over", "price": 1.62, "point": 2.5}, {"name": "Under", "price": 2.2, "point": 2.5}]}, {"key": "btts", "last_update": "2023-08-20T13:58:58Z", "outcomes": [{"name": "Yes", "price": 1.57}, {"name": "No", "price": 2.3}]}]}, {"key": "unibet_eu", "title": "Unibet", "markets": [{"key": "totals", "last_update": "2023-08-20T13:58:03Z", "outcomes": [{"name": "Over", "price": 1.63, "point": 2.5}, {"name": "Under", "price": 2.28, "point": 2.5}]}]}]}