{"id": "847e44284a92da9263e8b81458db6ece", "sport_key": "soccer_uefa_champs_league_qualification", "sport_title": "UEFA Champions League Qualification", "commence_time": "2023-08-23T19:00:22Z", "home_team": "Molde FK", "away_team": "Galatasaray", "bookmakers": [{"key": "pinnacle", "title": "Pinnacle", "markets": [{"key": "totals", "last_update": "2023-08-23T19:29:28Z", "outcomes": [{"name": "Over", "price": 1.84, "point": 3.0}, {"name": "Under", "price": 2.04, "point": 3.0}]}]}, {"key": "unibet_eu", "title": "Unibet", "markets": [{"key": "totals", "last_update": "2023-08-23T19:29:28Z", "outcomes": [{"name": "Over", "price": 1.62, "point": 4.5}, {"name": "Under", "price": 2.15, "point": 4.5}]}]}]}