{"id": "c76433e1322627017a497ddae88842ab", "sport_key": "soccer_usa_mls", "sport_title": "MLS", "commence_time": "2023-09-24T02:30:00Z", "home_team": "San Jose Earthquakes", "away_team": "Nashville SC", "bookmakers": [{"key": "nordicbet", "title": "Nordic Bet", "markets": [{"key": "totals", "last_update": "2023-09-24T02:49:13Z", "outcomes": [{"name": "Over", "price": 7.5, "point": 4.5}, {"name": "Under", "price": 1.06, "point": 4.5}]}]}, {"key": "unibet_eu", "title": "Unibet", "markets": [{"key": "totals", "last_update": "2023-09-24T02:49:29Z", "outcomes": [{"name": "Over", "price": 1.95, "point": 2.5}, {"name": "Under", "price": 1.8, "point": 2.5}]}]}, {"key": "matchbook", "title": "Matchbook", "markets": [{"key": "totals", "last_update": "2023-09-24T02:49:13Z", "outcomes": [{"name": "Over", "price": 2.18, "point": 2.5}, {"name": "Under", "price": 1.79, "point": 2.5}]}]}, {"key": "pinnacle", "title": "Pinnacle", "markets": [{"key": "totals", "last_update": "2023-09-24T02:43:48Z", "outcomes": [{"name": "Over", "price": 1.96, "point": 2.5}, {"name": "Under", "price": 1.93, "point": 2.5}]}]}, {"key": "betonlineag", "title": "BetOnline.ag", "markets": [{"key": "totals", "last_update": "2023-09-24T02:40:39Z", "outcomes": [{"name": "Over", "price": 1.94, "point": 2.5}, {"name": "Under", "price": 1.88, "point": 2.5}]}]}]}