{"id": "15f766252e0fc1830e9a05082f4baefb", "sport_key": "soccer_england_league2", "sport_title": "League 2", "commence_time": "2023-09-23T14:00:00Z", "home_team": "Newport County", "away_team": "Bradford City", "bookmakers": [{"key": "onexbet", "title": "1xBet", "markets": [{"key": "totals", "last_update": "2023-09-23T13:13:40Z", "outcomes": [{"name": "Over", "price": 2.08, "point": 2.5}, {"name": "Under", "price": 1.74, "point": 2.5}]}, {"key": "btts", "last_update": "2023-09-23T13:13:40Z", "outcomes": [{"name": "Yes", "price": 1.83}, {"name": "No", "price": 1.93}]}]}, {"key": "pinnacle", "title": "Pinnacle", "markets": [{"key": "totals", "last_update": "2023-09-23T13:13:40Z", "outcomes": [{"name": "Over", "price": 1.86, "point": 2.25}, {"name": "Under", "price": 2.01, "point": 2.25}]}]}, {"key": "williamhill", "title": "William Hill", "markets": [{"key": "totals", "last_update": "2023-09-23T13:13:44Z", "outcomes": [{"name": "Over", "price": 2.1, "point": 2.5}, {"name": "Under", "price": 1.67, "point": 2.5}]}, {"key": "btts", "last_update": "2023-09-23T13:13:44Z", "outcomes": [{"name": "Yes", "price": 1.8}, {"name": "No", "price": 1.91}]}]}, {"key": "matchbook", "title": "Matchbook", "markets": [{"key": "totals", "last_update": "2023-09-23T13:13:40Z", "outcomes": [{"name": "Over", "price": 2.16, "point": 2.5}, {"name": "Under", "price": 1.81, "point": 2.5}]}]}, {"key": "betonlineag", "title": "BetOnline.ag", "markets": [{"key": "totals", "last_update": "2023-09-23T13:13:40Z", "outcomes": [{"name": "Over", "price": 1.88, "point": 2.25}, {"name": "Under", "price": 1.94, "point": 2.25}]}]}, {"key": "unibet_eu", "title": "Unibet", "markets": [{"key": "totals", "last_update": "2023-09-23T13:13:41Z", "outcomes": [{"name": "Over", "price": 2.0, "point": 2.5}, {"name": "Under", "price": 1.74, "point": 2.5}]}]}]}