{"id": "21fc1f1813d5c73f13dd5133ec208d49", "sport_key": "soccer_germany_bundesliga2", "sport_title": "Bundesliga 2 - Germany", "commence_time": "2023-08-27T11:30:19Z", "home_team": "FC St. Pauli", "away_team": "1. FC Magdeburg", "bookmakers": [{"key": "pinnacle", "title": "Pinnacle", "markets": [{"key": "totals", "last_update": "2023-08-27T12:29:59Z", "outcomes": [{"name": "Over", "price": 1.89, "point": 1.5}, {"name": "Under", "price": 1.99, "point": 1.5}]}]}, {"key": "unibet_eu", "title": "Unibet", "markets": [{"key": "totals", "last_update": "2023-08-27T12:30:00Z", "outcomes": [{"name": "Over", "price": 1.71, "point": 1.5}, {"name": "Under", "price": 2.04, "point": 1.5}]}]}, {"key": "matchbook", "title": "Matchbook", "markets": [{"key": "totals", "last_update": "2023-08-27T12:29:58Z", "outcomes": [{"name": "Over", "price": 1.93, "point": 1.5}, {"name": "Under", "price": 2.04, "point": 1.5}]}]}]}