{"id": "78885cff717cb4be1f14b2ab1db47931", "sport_key": "soccer_sweden_superettan", "sport_title": "Superettan - Sweden", "commence_time": "2023-09-27T17:00:00Z", "home_team": "\u00d6stersunds FK", "away_team": "IK Brage", "bookmakers": [{"key": "unibet_eu", "title": "Unibet", "markets": [{"key": "totals", "last_update": "2023-09-27T16:15:52Z", "outcomes": [{"name": "Over", "price": 1.88, "point": 2.5}, {"name": "Under", "price": 1.92, "point": 2.5}]}]}, {"key": "onexbet", "title": "1xBet", "markets": [{"key": "totals", "last_update": "2023-09-27T16:15:51Z", "outcomes": [{"name": "Over", "price": 1.9, "point": 2.5}, {"name": "Under", "price": 1.85, "point": 2.5}]}, {"key": "btts", "last_update": "2023-09-27T16:15:51Z", "outcomes": [{"name": "Yes", "price": 1.71}, {"name": "No", "price": 2.08}]}]}, {"key": "williamhill", "title": "William Hill", "markets": [{"key": "totals", "last_update": "2023-09-27T16:11:56Z", "outcomes": [{"name": "Over", "price": 1.91, "point": 2.5}, {"name": "Under", "price": 1.8, "point": 2.5}]}, {"key": "btts", "last_update": "2023-09-27T16:11:56Z", "outcomes": [{"name": "Yes", "price": 1.73}, {"name": "No", "price": 2.0}]}]}, {"key": "nordicbet", "title": "Nordic Bet", "markets": [{"key": "totals", "last_update": "2023-09-27T16:15:51Z", "outcomes": [{"name": "Over", "price": 1.95, "point": 2.5}, {"name": "Under", "price": 1.85, "point": 2.5}]}]}, {"key": "pinnacle", "title": "Pinnacle", "markets": [{"key": "totals", "last_update": "2023-09-27T16:15:51Z", "outcomes": [{"name": "Over", "price": 1.96, "point": 2.5}, {"name": "Under", "price": 1.87, "point": 2.5}]}]}, {"key": "matchbook", "title": "Matchbook", "markets": [{"key": "totals", "last_update": "2023-09-27T16:15:51Z", "outcomes": [{"name": "Over", "price": 2.04, "point": 2.5}, {"name": "Under", "price": 1.89, "point": 2.5}]}]}, {"key": "betonlineag", "title": "BetOnline.ag", "markets": [{"key": "totals", "last_update": "2023-09-27T16:15:51Z", "outcomes": [{"name": "Over", "price": 1.93, "point": 2.5}, {"name": "Under", "price": 1.89, "point": 2.5}]}]}]}