{"id": "0535394c5ff731fe0d22a45e193f6814", "sport_key": "soccer_italy_serie_a", "sport_title": "Serie A - Italy", "commence_time": "2023-09-27T16:30:02Z", "home_team": "Hellas Verona FC", "away_team": "Atalanta BC", "bookmakers": [{"key": "pinnacle", "title": "Pinnacle", "markets": [{"key": "totals", "last_update": "2023-09-27T16:54:13Z", "outcomes": [{"name": "Over", "price": 2.1, "point": 3.0}, {"name": "Under", "price": 1.81, "point": 3.0}]}]}, {"key": "unibet_eu", "title": "Unibet", "markets": [{"key": "totals", "last_update": "2023-09-27T16:54:14Z", "outcomes": [{"name": "Over", "price": 1.6, "point": 2.5}, {"name": "Under", "price": 2.28, "point": 2.5}]}]}, {"key": "matchbook", "title": "Matchbook", "markets": [{"key": "totals", "last_update": "2023-09-27T16:54:12Z", "outcomes": [{"name": "Over", "price": 1.75, "point": 2.5}, {"name": "Under", "price": 2.28, "point": 2.5}]}]}]}