{"id": "87c10e296bb586fc2477511d17113a7a", "sport_key": "soccer_usa_mls", "sport_title": "MLS", "commence_time": "2023-09-28T01:39:11Z", "home_team": "Colorado Rapids", "away_team": "Vancouver Whitecaps FC", "bookmakers": [{"key": "pinnacle", "title": "Pinnacle", "markets": [{"key": "totals", "last_update": "2023-09-28T02:59:49Z", "outcomes": [{"name": "Over", "price": 1.92, "point": 3.0}, {"name": "Under", "price": 1.97, "point": 3.0}]}]}, {"key": "nordicbet", "title": "Nordic Bet", "markets": [{"key": "totals", "last_update": "2023-09-28T02:59:49Z", "outcomes": [{"name": "Over", "price": 65.0, "point": 6.5}, {"name": "Under", "price": 1.0, "point": 6.5}]}]}, {"key": "matchbook", "title": "Matchbook", "markets": [{"key": "totals", "last_update": "2023-09-28T02:59:49Z", "outcomes": [{"name": "Over", "price": 1.52, "point": 2.5}, {"name": "Under", "price": 2.84, "point": 2.5}]}]}, {"key": "unibet_eu", "title": "Unibet", "markets": [{"key": "totals", "last_update": "2023-09-28T02:59:50Z", "outcomes": [{"name": "Over", "price": 1.38, "point": 2.5}, {"name": "Under", "price": 2.9, "point": 2.5}]}]}]}