{"id": "acbcab7b8027793a1f18c3220db1aefd", "sport_key": "soccer_china_superleague", "sport_title": "Super League - China", "commence_time": "2023-09-29T09:30:00Z", "home_team": "Cangzhou Mighty Lions", "away_team": "Meizhou Hakka", "bookmakers": [{"key": "pinnacle", "title": "Pinnacle", "markets": [{"key": "totals", "last_update": "2023-09-29T09:29:03Z", "outcomes": [{"name": "Over", "price": 2.0, "point": 3.0}, {"name": "Under", "price": 1.85, "point": 3.0}]}]}, {"key": "onexbet", "title": "1xBet", "markets": [{"key": "totals", "last_update": "2023-09-29T09:28:13Z", "outcomes": [{"name": "Over", "price": 1.57, "point": 2.5}, {"name": "Under", "price": 2.39, "point": 2.5}]}, {"key": "btts", "last_update": "2023-09-29T09:28:13Z", "outcomes": [{"name": "Yes", "price": 1.5}, {"name": "No", "price": 2.58}]}]}, {"key": "matchbook", "title": "Matchbook", "markets": [{"key": "totals", "last_update": "2023-09-29T09:29:02Z", "outcomes": [{"name": "Over", "price": 1.66, "point": 2.5}, {"name": "Under", "price": 2.42, "point": 2.5}]}]}, {"key": "betonlineag", "title": "BetOnline.ag", "markets": [{"key": "totals", "last_update": "2023-09-29T09:29:37Z", "outcomes": [{"name": "Over", "price": 1.97, "point": 3.0}, {"name": "Under", "price": 1.85, "point": 3.0}]}]}, {"key": "unibet_eu", "title": "Unibet", "markets": [{"key": "totals", "last_update": "2023-09-29T09:32:30Z", "outcomes": [{"name": "Over", "price": 1.57, "point": 2.5}, {"name": "Under", "price": 2.23, "point": 2.5}]}]}]}