{"id": "d4e8b1e4907b23a050b099399ecfd804", "sport_key": "soccer_mexico_ligamx", "sport_title": "Liga MX", "commence_time": "2023-09-30T03:07:38Z", "home_team": "Atl\u00e9tico San Luis", "away_team": "Cruz Azul", "bookmakers": [{"key": "unibet_eu", "title": "Unibet", "markets": [{"key": "totals", "last_update": "2023-09-30T04:28:54Z", "outcomes": [{"name": "Over", "price": 1.35, "point": 1.5}, {"name": "Under", "price": 3.0, "point": 1.5}]}]}, {"key": "pinnacle", "title": "Pinnacle", "markets": [{"key": "totals", "last_update": "2023-09-30T04:28:53Z", "outcomes": [{"name": "Over", "price": 1.98, "point": 2.0}, {"name": "Under", "price": 1.91, "point": 2.0}]}]}]}