{"id": "400add7c13b1c56b92de9bfa297d7704", "sport_key": "soccer_portugal_primeira_liga", "sport_title": "Primeira Liga - Portugal", "commence_time": "2023-09-30T19:33:10Z", "home_team": "SC Farense", "away_team": "Sporting Lisbon", "bookmakers": [{"key": "nordicbet", "title": "Nordic Bet", "markets": [{"key": "totals", "last_update": "2023-09-30T20:47:31Z", "outcomes": [{"name": "Over", "price": 1.71, "point": 4.5}, {"name": "Under", "price": 2.04, "point": 4.5}]}]}, {"key": "unibet_eu", "title": "Unibet", "markets": [{"key": "totals", "last_update": "2023-09-30T20:49:52Z", "outcomes": [{"name": "Over", "price": 1.88, "point": 4.5}, {"name": "Under", "price": 1.82, "point": 4.5}]}]}, {"key": "pinnacle", "title": "Pinnacle", "markets": [{"key": "totals", "last_update": "2023-09-30T20:52:15Z", "outcomes": [{"name": "Over", "price": 2.02, "point": 4.75}, {"name": "Under", "price": 1.85, "point": 4.75}]}]}, {"key": "matchbook", "title": "Matchbook", "markets": [{"key": "totals", "last_update": "2023-09-30T20:49:51Z", "outcomes": [{"name": "Over", "price": 1.98, "point": 4.5}, {"name": "Under", "price": 2.02, "point": 4.5}]}]}]}