{"id": "25aa4de02233b5f5ffeeb44be1492d0d", "sport_key": "soccer_spl", "sport_title": "Premiership - Scotland", "commence_time": "2023-09-30T11:31:23Z", "home_team": "Motherwell", "away_team": "Celtic", "bookmakers": [{"key": "nordicbet", "title": "Nordic Bet", "markets": [{"key": "totals", "last_update": "2023-09-30T11:53:53Z", "outcomes": [{"name": "Over", "price": 1.98, "point": 2.5}, {"name": "Under", "price": 1.75, "point": 2.5}]}]}, {"key": "pinnacle", "title": "Pinnacle", "markets": [{"key": "totals", "last_update": "2023-09-30T11:53:53Z", "outcomes": [{"name": "Over", "price": 1.9, "point": 2.5}, {"name": "Under", "price": 1.99, "point": 2.5}]}]}, {"key": "unibet_eu", "title": "Unibet", "markets": [{"key": "totals", "last_update": "2023-09-30T11:53:54Z", "outcomes": [{"name": "Over", "price": 2.02, "point": 2.5}, {"name": "Under", "price": 1.77, "point": 2.5}]}]}, {"key": "matchbook", "title": "Matchbook", "markets": [{"key": "totals", "last_update": "2023-09-30T11:53:53Z", "outcomes": [{"name": "Over", "price": 2.1, "point": 2.5}, {"name": "Under", "price": 1.78, "point": 2.5}]}]}]}