{"id": "57c219a511aa38ec1c47f39e9833d17d", "sport_key": "soccer_turkey_super_league", "sport_title": "Turkey Super League", "commence_time": "2023-09-30T13:00:00Z", "home_team": "Istanbulspor", "away_team": "Antalyaspor", "bookmakers": [{"key": "nordicbet", "title": "Nordic Bet", "markets": [{"key": "totals", "last_update": "2023-09-30T11:43:47Z", "outcomes": [{"name": "Over", "price": 1.76, "point": 2.5}, {"name": "Under", "price": 1.97, "point": 2.5}]}]}, {"key": "onexbet", "title": "1xBet", "markets": [{"key": "totals", "last_update": "2023-09-30T11:42:15Z", "outcomes": [{"name": "Over", "price": 1.83, "point": 2.5}, {"name": "Under", "price": 2.08, "point": 2.5}]}, {"key": "btts", "last_update": "2023-09-30T11:42:15Z", "outcomes": [{"name": "Yes", "price": 1.66}, {"name": "No", "price": 2.16}]}]}, {"key": "pinnacle", "title": "Pinnacle", "markets": [{"key": "totals", "last_update": "2023-09-30T11:43:47Z", "outcomes": [{"name": "Over", "price": 2.03, "point": 2.75}, {"name": "Under", "price": 1.86, "point": 2.75}]}]}, {"key": "unibet_eu", "title": "Unibet", "markets": [{"key": "totals", "last_update": "2023-09-30T11:43:48Z", "outcomes": [{"name": "Over", "price": 1.85, "point": 2.5}, {"name": "Under", "price": 1.94, "point": 2.5}]}]}, {"key": "matchbook", "title": "Matchbook", "markets": [{"key": "totals", "last_update": "2023-09-30T11:43:46Z", "outcomes": [{"name": "Over", "price": 1.85, "point": 2.5}, {"name": "Under", "price": 2.12, "point": 2.5}]}]}, {"key": "betonlineag", "title": "BetOnline.ag", "markets": [{"key": "totals", "last_update": "2023-09-30T11:43:47Z", "outcomes": [{"name": "Over", "price": 2.0, "point": 2.75}, {"name": "Under", "price": 1.83, "point": 2.75}]}]}]}